topsis_naman_102303496/__init__.py
topsis_naman_102303496/__main__.py
topsis_naman_102303496/topsis.py
topsis_naman_102303496-1.0.0.dist-info/licenses/LICENSE
topsis_naman_102303496-1.0.0.dist-info/METADATA
topsis_naman_102303496-1.0.0.dist-info/WHEEL
topsis_naman_102303496-1.0.0.dist-info/entry_points.txt
topsis_naman_102303496-1.0.0.dist-info/top_level.txt
topsis_naman_102303496-1.0.0.dist-info/RECORD
