Metadata-Version: 2.4
Name: Topsis-Naman-102303496
Version: 1.0.0
Summary: A Python package for TOPSIS (Technique for Order of Preference by Similarity to Ideal Solution)
Author-email: Naman Bansal <naman@example.com>
License: MIT
Project-URL: Homepage, https://github.com/namanbansal/Topsis-Naman-102303496
Classifier: Programming Language :: Python :: 3
Classifier: License :: OSI Approved :: MIT License
Classifier: Operating System :: OS Independent
Requires-Python: >=3.7
License-File: LICENSE
Requires-Dist: pandas
Requires-Dist: numpy
Dynamic: license-file
